[
  {
    "index": 0,
    "original": "1-בניה ופיתוח - אודות.html",
    "saved_as": "file_0000.html",
    "size": 26687
  },
  {
    "index": 1,
    "original": "2-בניה ופיתוח - פרויקטים.html",
    "saved_as": "file_0001.html",
    "size": 29192
  },
  {
    "index": 2,
    "original": "3-בניה ופיתוח - המלצות.html",
    "saved_as": "file_0002.html",
    "size": 22260
  },
  {
    "index": 3,
    "original": "4-בניה ופיתוח - פתיחה / טעינה.html",
    "saved_as": "file_0003.html",
    "size": 24287
  },
  {
    "index": 4,
    "original": "5-בניה ופיתוח - דף הבית.html",
    "saved_as": "file_0004.html",
    "size": 20041
  },
  {
    "index": 5,
    "original": "6-בניה ופיתוח - לקוחות.html",
    "saved_as": "file_0005.html",
    "size": 24189
  },
  {
    "index": 6,
    "original": "7-בניה ופיתוח - צור קשר.html",
    "saved_as": "file_0006.html",
    "size": 22011
  }
]